protein_watermark/__init__.py
protein_watermark/base.py
protein_watermark/delta_gumble.py
protein_watermark/transformer.py
protein_watermark/watermark.py
protein_watermark-0.1.dist-info/LICENSE
protein_watermark-0.1.dist-info/METADATA
protein_watermark-0.1.dist-info/WHEEL
protein_watermark-0.1.dist-info/top_level.txt
protein_watermark-0.1.dist-info/RECORD
